{
  "1001": "Ice",
  "1002": "Wind",
  "1003": "Fire",
  "1004": "Imaginary",
  "1005": "Thunder",
  "1006": "Quantum",
  "1008": "Thunder",
  "1009": "Fire",
  "1013": "Ice",
  "1101": "Wind",
  "1102": "Quantum",
  "1103": "Thunder",
  "1104": "Ice",
  "1105": "Physical",
  "1106": "Ice",
  "1107": "Physical",
  "1108": "Wind",
  "1109": "Fire",
  "1111": "Physical",
  "1201": "Quantum",
  "1202": "Thunder",
  "1203": "Imaginary",
  "1204": "Thunder",
  "1205": "Wind",
  "1206": "Physical",
  "1207": "Imaginary",
  "1208": "Quantum",
  "1209": "Ice",
  "1211": "Thunder",
  "1213": "Imaginary",
  "1110": "Quantum",
  "1212": "Ice",
  "1112": "Fire",
  "1210": "Fire",
  "1217": "Wind",
  "1302": "Physical",
  "1215": "Physical",
  "1303": "Ice",
  "1305": "Imaginary",
  "1214": "Quantum",
  "1307": "Wind",
  "1306": "Quantum",
  "1312": "Ice",
  "1308": "Thunder",
  "1304": "Imaginary",
  "1301": "Fire",
  "1309": "Physical",
  "1315": "Physical",
  "1310": "Fire",
  "1314": "Quantum",
  "1221": "Physical",
  "1218": "Fire",
  "1223": "Thunder",
  "1220": "Wind",
  "1222": "Fire",
  "1317": "Imaginary",
  "1225": "Fire",
  "1313": "Imaginary",
  "1401": "Ice",
  "1402": "Thunder",
  "8001": "Physical",
  "8002": "Physical",
  "8003": "Fire",
  "8004": "Fire",
  "8007": "Ice",
  "8008": "Ice",
  "9100": "Physical"
}
